[
    {
        "_id": [
            "_role/id",
            "endUser"
        ],
        "rules": [
            "_rule$fullAccessOwnListData",
            "_rule$transactAccessTaskData",
            "_rule$canViewAssociatedLists",
            "_rule$canViewAllTasks",
            "_rule$canEditCompletionStatus",
            "_rule$canViewAssignees"
        ]
    },
    {
        "_id": "_rule$fullAccessOwnListData",
        "id": "fullAccessOwnListData",
        "doc": "A _user with this rule can only view their own list data",
        "fns": [
            "_fn$fullAccessOwnListData"
        ],
        "ops": [
            "all"
        ],
        "collection": "list",
        "predicates": [
            "*"
        ]
    },
    {
        "_id": "_fn$fullAccessOwnListData",
        "name": "fullAccessOwnListData?",
        "doc": "A _user can query and edit their own list data",
        "code": "(relationship? (?sid) [\"list/listOwner\" \"_user/auth\"] (?auth_id))"
    },
    {
        "_id": "_rule$transactAccessTaskData",
        "id": "transactAccessTaskData",
        "doc": "A _user with this rule view and edit task data",
        "fns": [
            "_fn$transactAccessTaskData"
        ],
        "ops": [
            "transact"
        ],
        "collection": "task",
        "predicates": [
            "*"
        ]
    },
    {
        "_id": "_fn$transactAccessTaskData",
        "name": "transactAccessTaskData?",
        "doc": "A _user can edit task data linked to their list",
        "code": "(relationship? (?sid) [\"task/issuedBy\" \"list/listOwner\" \"_user/auth\"] (?auth_id))"
    },
    {
        "_id": "_rule$canViewAssociatedLists",
        "id": "canViewAssociatedLists",
        "doc": "A _user with this rule can view the list data that they are associated with",
        "fns": [
            "_fn$canViewAssociatedLists"
        ],
        "ops": [
            "query"
        ],
        "collection": "list",
        "predicates": [
            "*"
        ]
    },
    {
        "_id": "_fn$canViewAssociatedLists",
        "name": "canViewAssociatedLists?",
        "doc": "A _user can view the list data that they are associated with",
        "code": "(relationship? (?sid) [\"list/tasks\" \"task/assignedTo\" \"assignee/user\" \"_user/auth\"] (?auth_id))"
    },
    {
        "_id": "_rule$canViewAllTasks",
        "id": "canViewAllTasks",
        "doc": "A _user with this rule can view task info assigned to them",
        "fns": [
            [
                "_fn/name",
                "true"
            ]
        ],
        "ops": [
            "query"
        ],
        "collection": "task",
        "predicates": [
            "*"
        ]
    },
    {
        "_id": "_rule$canEditCompletionStatus",
        "id": "canEditCompletionStatus",
        "doc": "A _user with this rule can update a task's completion status if tied to their user",
        "fns": [
            "_fn$canEditCompletionStatus"
        ],
        "ops": [
            "transact"
        ],
        "collection": "task",
        "predicates": [
            "task/isCompleted"
        ]
    },
    {
        "_id": "_fn$canEditCompletionStatus",
        "name": "canEditCompletionStatus?",
        "doc": "A _user can edit a task's completion status if tied to their user",
        "code": "(relationship? (?sid) [\"task/assignedTo\" \"assignee/user\" \"_user/auth\"] (?auth_id))"
    },
    {
        "_id": "_rule$canViewAssignees",
        "id": "canViewAssignees",
        "doc": "A _user with this rule can view all assignee data",
        "fns": [
            [
                "_fn/name",
                "true"
            ]
        ],
        "ops": [
            "query"
        ],
        "collection": "assignee",
        "predicates": [
            "*"
        ]
    }
]